pytestmar/__init__.py
pytestmar/__main__.py
pytestmar/cli.py
pytestmar-0.0.0.dist-info/AUTHORS.rst
pytestmar-0.0.0.dist-info/LICENSE
pytestmar-0.0.0.dist-info/METADATA
pytestmar-0.0.0.dist-info/WHEEL
pytestmar-0.0.0.dist-info/entry_points.txt
pytestmar-0.0.0.dist-info/top_level.txt
pytestmar-0.0.0.dist-info/RECORD
