Metadata-Version: 2.1
Name: pytestmar
Version: 0.0.0
Summary: first packagin attempt
Home-page: https://github.com/Elamraoui-Sohayb/python-pytestmar
Author: Elamraoui-Sohayb
Author-email: elamraoui.sohayb@gmail.com
License: MIT
Project-URL: Documentation, https://python-pytestmar.readthedocs.io/
Project-URL: Changelog, https://python-pytestmar.readthedocs.io/en/latest/changelog.html
Project-URL: Issue Tracker, https://github.com/Elamraoui-Sohayb/python-pytestmar/issues
Platform: UNKNOWN
Classifier: Development Status :: 5 - Production/Stable
Classifier: Intended Audience :: Developers
Classifier: License :: OSI Approved :: MIT License
Classifier: Operating System :: Unix
Classifier: Operating System :: POSIX
Classifier: Operating System :: Microsoft :: Windows
Classifier: Programming Language :: Python
Classifier: Programming Language :: Python :: 3.5
Classifier: Programming Language :: Python :: 3.6
Classifier: Programming Language :: Python :: 3.7
Classifier: Programming Language :: Python :: 3.8
Classifier: Programming Language :: Python :: 3.9
Classifier: Programming Language :: Python :: Implementation :: CPython
Classifier: Programming Language :: Python :: Implementation :: PyPy
Classifier: Topic :: Utilities
Requires-Python: >=2.7, !=3.0.*, !=3.1.*, !=3.2.*, !=3.3.*, !=3.4.*
